OSMEvolution/__init__.py
OSMEvolution/collect.py
OSMEvolution/request.py
OSMEvolution/restructure.py
OSMEvolution-1.0.dist-info/LICENSE
OSMEvolution-1.0.dist-info/METADATA
OSMEvolution-1.0.dist-info/WHEEL
OSMEvolution-1.0.dist-info/top_level.txt
OSMEvolution-1.0.dist-info/RECORD
