Metadata-Version: 2.1
Name: OSMEvolution
Version: 1.0
Summary: A package for receiving and restructuring OSM historic data conveniently
Home-page: https://github.com/le0x99/OSMEvolution/
Author: Leonard Vorbeck
Author-email: leomxyy@googlemail.com
License: UNKNOWN
Platform: UNKNOWN
Classifier: Development Status :: 4 - Beta
Classifier: License :: OSI Approved :: MIT License
Classifier: Programming Language :: Python
Classifier: Programming Language :: Python :: 3.5
Classifier: Programming Language :: Python :: 3.6
Classifier: Programming Language :: Python :: 3.7
Classifier: Programming Language :: Python :: 3.8
Classifier: Programming Language :: Python :: 3.9
Classifier: Topic :: Software Development :: Libraries
Classifier: Topic :: Software Development :: Libraries :: Python Modules
Classifier: Intended Audience :: Developers
License-File: LICENSE
Requires-Dist: pandas (>=0.24.2)
Requires-Dist: requests (>=2.22.0)
Requires-Dist: tqdm (>=4.35.0)
Requires-Dist: osmapi (>=1.2.2)
